easytensor/__init__.py
easytensor/auth.py
easytensor/config.py
easytensor/constants.py
easytensor/upload.py
easytensor/urls.py
easytensor/pytorch/__init__.py
easytensor/pytorch/upload.py
easytensor/tensorflow/__init__.py
easytensor/tensorflow/upload.py
easytensor/transformers/__init__.py
easytensor/transformers/upload.py
easytensor-0.0.10.dist-info/LICENSE
easytensor-0.0.10.dist-info/METADATA
easytensor-0.0.10.dist-info/WHEEL
easytensor-0.0.10.dist-info/top_level.txt
easytensor-0.0.10.dist-info/RECORD
