Metadata-Version: 2.1
Name: easytensor
Version: 0.0.10
Summary: The official python cient of EasyTensor
Home-page: https://github.com/EasyTensor/python-client
Author: Kamal Kamalaldin
Author-email: kamal@easytensor.com
License: UNKNOWN
Platform: UNKNOWN
Classifier: Programming Language :: Python :: 3
Classifier: License :: OSI Approved :: MIT License
Classifier: Operating System :: OS Independent
Requires-Python: >=3.6
Requires-Dist: requests
Requires-Dist: tensorflow
Requires-Dist: torch
Requires-Dist: transformers
Requires-Dist: tqdm
Requires-Dist: pyflakes
